numflow/__init__.py
numflow/compute.cpython-39-darwin.so
numflow/dataset.py
numflow/encoder.py
numflow/exceptions.py
numflow/geometry.py
numflow/kernels.py
numflow/visualization.py
numflow-1.0.0.dist-info/METADATA
numflow-1.0.0.dist-info/WHEEL
numflow-1.0.0.dist-info/top_level.txt
numflow-1.0.0.dist-info/RECORD
