Metadata-Version: 2.1
Name: numflow
Version: 1.0.0
Summary: Transforming vector fields
Home-page: https://github.com/vojtatom/numflow.py
Author: Vojtěch Tomas
Author-email: hello@vojtatom.cz
License: MIT
Classifier: License :: OSI Approved :: MIT License
Classifier: Programming Language :: Python :: 3
Classifier: Programming Language :: Python :: 3.8
Requires-Python: >=3.8
